sphinx_ext_substitution/__init__.py
sphinx_ext_substitution/_version.py
sphinx_ext_substitution/get_replacements.py
sphinx_ext_substitution/substitution.py
sphinx_ext_substitution/test_basic.py
sphinx_ext_substitution/util.py
sphinx_ext_substitution/_static/sphinx_ext_substitution.css
sphinx_ext_substitution-0.1.3.dist-info/LICENSE
sphinx_ext_substitution-0.1.3.dist-info/METADATA
sphinx_ext_substitution-0.1.3.dist-info/WHEEL
sphinx_ext_substitution-0.1.3.dist-info/top_level.txt
sphinx_ext_substitution-0.1.3.dist-info/RECORD
