Metadata-Version: 2.1
Name: sphinx-ext-substitution
Version: 0.1.3
Summary: Sphinx extension for substituting variables
Home-page: https://github.com/NordicHPC/sphinx_ext_substitution
Author: Richard Darst
License: UNKNOWN
Keywords: sphinx-extension
Platform: UNKNOWN
Classifier: Programming Language :: Python :: 3
Classifier: Development Status :: 4 - Beta
Classifier: Framework :: Sphinx
Classifier: Framework :: Sphinx :: Extension
Classifier: Operating System :: OS Independent
Requires-Python: >=2.7, !=3.0.*, !=3.1.*, !=3.2.*, !=3.3.*, !=3.4.*,
License-File: LICENSE
Requires-Dist: PyYAML
Requires-Dist: Sphinx
Requires-Dist: docutils (!=0.15)
Requires-Dist: jsonpath-ng
